setup.py
server/__init__.py
server/setup_server.py
server/common/__init__.py
server/common/decorators.py
server/common/descriptors.py
server/common/errors.py
server/common/metaclasses.py
server/common/utils.py
server/common/variables.py
server/doc/__init__.py
server/doc/source/__init__.py
server/doc/source/conf.py
server/gui/__init__.py
server/gui/add_user.py
server/gui/config_window.py
server/gui/main_window.py
server/gui/remove_user.py
server/gui/stat_window.py
server/main/__init__.py
server/main/core.py
server/main/database.py
server/main/server_start.py
server/project_logs/__init__.py
vyatkin_chat_server.egg-info/PKG-INFO
vyatkin_chat_server.egg-info/SOURCES.txt
vyatkin_chat_server.egg-info/dependency_links.txt
vyatkin_chat_server.egg-info/requires.txt
vyatkin_chat_server.egg-info/top_level.txt