Metadata-Version: 1.0
Name: vyatkin-chat-server
Version: 0.0.1
Summary: vyatkin_chat_server
Home-page: UNKNOWN
Author: Vyatkin M.
Author-email: UNKNOWN
License: UNKNOWN
Platform: UNKNOWN
